upvest_investment_api/__init__.py
upvest_investment_api/env_settings.py
upvest_investment_api/file_download.py
upvest_investment_api/http_message_signatures.py
upvest_investment_api/requests_auth.py
upvest_investment_api-0.0.1.dist-info/METADATA
upvest_investment_api-0.0.1.dist-info/WHEEL
upvest_investment_api-0.0.1.dist-info/licenses/LICENSE
upvest_investment_api-0.0.1.dist-info/RECORD
