Metadata-Version: 2.1
Name: upvest_investment_api
Version: 0.0.1
Summary: Utility code for interacting with the Upvest Investment API, mainly HTTP Message Signatures
Project-URL: Homepage, https://github.com/upvestco/http-signature-examples/tree/main/Python
Author-email: Raphael Huefner <raphael@upvest.co>, Geoffrey Teale <geoffrey@upvest.co>
Maintainer-email: Raphael Huefner <raphael@upvest.co>, Geoffrey Teale <geoffrey@upvest.co>
License:                                  Apache License
License-File: LICENSE
Classifier: Development Status :: 4 - Beta
Classifier: Intended Audience :: Developers
Classifier: Intended Audience :: Financial and Insurance Industry
Classifier: License :: OSI Approved :: Apache Software License
Classifier: Operating System :: OS Independent
Classifier: Programming Language :: Python :: 3 :: Only
Classifier: Topic :: Office/Business :: Financial :: Investment
Requires-Python: >=3.10
Requires-Dist: cryptography>=41.0.3
Provides-Extra: env-settings
Requires-Dist: environs>=9.5.0; extra == 'env-settings'
Provides-Extra: file-download
Requires-Dist: pgpy>=0.6.0; extra == 'file-download'
Requires-Dist: requests>=2.31.0; extra == 'file-download'
Provides-Extra: requests-auth
Requires-Dist: requests>=2.31.0; extra == 'requests-auth'
